moriarty/__init__.py
moriarty/envs.py
moriarty/exceptions.py
moriarty/log.py
moriarty/tools.py
moriarty/utils.py
moriarty/deploy/__init__.py
moriarty/deploy/cli.py
moriarty/deploy/config.py
moriarty/deploy/endpoint.py
moriarty/deploy/sdk.py
moriarty/matrix/__init__.py
moriarty/matrix/cli.py
moriarty/matrix/connector/__init__.py
moriarty/matrix/connector/app.py
moriarty/matrix/connector/cli.py
moriarty/matrix/connector/config.py
moriarty/matrix/connector/invoker.py
moriarty/matrix/connector/params.py
moriarty/matrix/connector/sdk.py
moriarty/matrix/job_manager/__init__.py
moriarty/matrix/job_manager/bridge_wrapper.py
moriarty/matrix/job_manager/params.py
moriarty/matrix/job_manager/bridge/__init__.py
moriarty/matrix/job_manager/bridge/manager.py
moriarty/matrix/job_manager/bridge/plugin.py
moriarty/matrix/job_manager/bridge/impl/__init__.py
moriarty/matrix/job_manager/bridge/impl/sqs_bridge.py
moriarty/matrix/operator_/__init__.py
moriarty/matrix/operator_/alembic.ini
moriarty/matrix/operator_/api_app.py
moriarty/matrix/operator_/autoscaler.py
moriarty/matrix/operator_/callback.py
moriarty/matrix/operator_/callback_app.py
moriarty/matrix/operator_/cli.py
moriarty/matrix/operator_/config.py
moriarty/matrix/operator_/daemon.py
moriarty/matrix/operator_/dbutils.py
moriarty/matrix/operator_/enums_.py
moriarty/matrix/operator_/mixin.py
moriarty/matrix/operator_/operator_.py
moriarty/matrix/operator_/orm.py
moriarty/matrix/operator_/params.py
moriarty/matrix/operator_/rds.py
moriarty/matrix/operator_/tools.py
moriarty/matrix/operator_/alembic/README
moriarty/matrix/operator_/alembic/env.py
moriarty/matrix/operator_/alembic/script.py.mako
moriarty/matrix/operator_/alembic/versions/DO_NOT_DELETE
moriarty/matrix/operator_/spawner/__init__.py
moriarty/matrix/operator_/spawner/manager.py
moriarty/matrix/operator_/spawner/plugin.py
moriarty/matrix/operator_/spawner/impl/__init__.py
moriarty/matrix/operator_/spawner/impl/k8s.py
moriarty/mock/__init__.py
moriarty-1.0.0.dist-info/METADATA
moriarty-1.0.0.dist-info/WHEEL
moriarty-1.0.0.dist-info/entry_points.txt
moriarty-1.0.0.dist-info/licenses/LICENSE
moriarty-1.0.0.dist-info/RECORD
