Metadata-Version: 2.3
Name: moriarty
Version: 1.0.0
Summary: moriarty
Project-URL: Source, https://github.com/wh1isper/moriarty
Author-email: wh1isper <jizhongsheng957@gmail.com>
License: BSD 3-Clause License
Keywords: moriarty
Classifier: Programming Language :: Python :: 3
Classifier: Programming Language :: Python :: 3.10
Classifier: Programming Language :: Python :: 3.11
Classifier: Programming Language :: Python :: 3.12
Requires-Python: >=3.10
Requires-Dist: anyio
Requires-Dist: async-timeout; python_version < '3.11'
Requires-Dist: brq>=0.3.6
Requires-Dist: click
Requires-Dist: httpx
Requires-Dist: importlib-metadata
Requires-Dist: loguru
Requires-Dist: pydantic>=2
Provides-Extra: docs
Requires-Dist: autodoc-pydantic; extra == 'docs'
Requires-Dist: pydata-sphinx-theme; extra == 'docs'
Requires-Dist: sphinx; extra == 'docs'
Requires-Dist: sphinx-click; extra == 'docs'
Provides-Extra: matrix
Requires-Dist: alembic; extra == 'matrix'
Requires-Dist: asyncpg; extra == 'matrix'
Requires-Dist: boto3; extra == 'matrix'
Requires-Dist: escapism; extra == 'matrix'
Requires-Dist: fastapi; extra == 'matrix'
Requires-Dist: jinja2; extra == 'matrix'
Requires-Dist: kubernetes-asyncio; extra == 'matrix'
Requires-Dist: pluggy; extra == 'matrix'
Requires-Dist: psycopg2-binary; extra == 'matrix'
Requires-Dist: sqlalchemy[asyncio]; extra == 'matrix'
Requires-Dist: uvicorn[standard]; extra == 'matrix'
Provides-Extra: service
Requires-Dist: alembic; extra == 'service'
Requires-Dist: asyncpg; extra == 'service'
Requires-Dist: escapism; extra == 'service'
Requires-Dist: fastapi; extra == 'service'
Requires-Dist: jinja2; extra == 'service'
Requires-Dist: kubernetes-asyncio; extra == 'service'
Requires-Dist: pluggy; extra == 'service'
Requires-Dist: psycopg2-binary; extra == 'service'
Requires-Dist: sqlalchemy[asyncio]; extra == 'service'
Requires-Dist: uvicorn[standard]; extra == 'service'
Provides-Extra: sqs
Requires-Dist: boto3; extra == 'sqs'
Provides-Extra: test
Requires-Dist: alembic; extra == 'test'
Requires-Dist: asyncpg; extra == 'test'
Requires-Dist: boto3; extra == 'test'
Requires-Dist: boto3-stubs[s3,sqs]; extra == 'test'
Requires-Dist: docker; extra == 'test'
Requires-Dist: escapism; extra == 'test'
Requires-Dist: fastapi; extra == 'test'
Requires-Dist: jinja2; extra == 'test'
Requires-Dist: kubernetes-asyncio; extra == 'test'
Requires-Dist: pluggy; extra == 'test'
Requires-Dist: psycopg2-binary; extra == 'test'
Requires-Dist: pytest; extra == 'test'
Requires-Dist: pytest-asyncio; extra == 'test'
Requires-Dist: pytest-cov; extra == 'test'
Requires-Dist: sqlalchemy[asyncio]; extra == 'test'
Requires-Dist: uvicorn[standard]; extra == 'test'
